{
  "type": "kendo-ui-mobile",
  "views": [
    {
      "type": "kendo-ui-mobile:view",
      "name": "loginView",
      "components": [],
      "title": "Login View",
      "addToNavigation": true,
      "icon": "home"
    },
    {
      "type": "kendo-ui-mobile:view",
      "name": "bolsView",
      "components": [],
      "title": "View Bols",
      "addToNavigation": true,
      "icon": "home"
    },
    {
      "type": "kendo-ui-mobile:view",
      "name": "bolSearchView",
      "components": [],
      "title": "Settings",
      "addToNavigation": true,
      "icon": "settings"
    }
  ],
  "dataProviders": [],
  "name": "kendoUiMobileApp",
  "navigation": "drawer",
  "view": "loginView",
  "skin": "flat"
}
